nomad_camels_driver_thorlabs_K10CR1/__init__.py
nomad_camels_driver_thorlabs_K10CR1/thorlabs_K10CR1.py
nomad_camels_driver_thorlabs_K10CR1/thorlabs_K10CR1_ophyd.py
nomad_camels_driver_thorlabs_K10CR1-0.1.1.dist-info/LICENSE.txt
nomad_camels_driver_thorlabs_K10CR1-0.1.1.dist-info/METADATA
nomad_camels_driver_thorlabs_K10CR1-0.1.1.dist-info/WHEEL
nomad_camels_driver_thorlabs_K10CR1-0.1.1.dist-info/top_level.txt
nomad_camels_driver_thorlabs_K10CR1-0.1.1.dist-info/RECORD
